setup.py
statistics_prob_distributions/Binomialdistribution.py
statistics_prob_distributions/Gaussiandistribution.py
statistics_prob_distributions/Generaldistribution.py
statistics_prob_distributions/__init__.py
statistics_prob_distributions.egg-info/PKG-INFO
statistics_prob_distributions.egg-info/SOURCES.txt
statistics_prob_distributions.egg-info/dependency_links.txt
statistics_prob_distributions.egg-info/not-zip-safe
statistics_prob_distributions.egg-info/top_level.txt