Metadata-Version: 2.1
Name: statistics-prob-distributions
Version: 1
Summary: Gaussian distributions and Binomial
Home-page: UNKNOWN
Author: Muhammad Rizwan
Author-email: xrizwanr@gmail.com
License: UNKNOWN
Platform: UNKNOWN
